{
  "descriptionHash": "0D3947F3482F6CCC67412A76D81EA76D625B2D6BBD33055AC1F5F866D2E0B2D555DE7FA3BEA10071FF093098F90A407063960C639B2F2340027BC873A7F64568",
  "descriptionLocation": "/home/vsts/work/1/s/msgraph-metadata/clean_beta_openapi/openapi.yaml",
  "lockFileVersion": "1.0.0",
  "kiotaVersion": "0.9.0.0",
  "clientClassName": "BaseGraphServiceClient",
  "clientNamespaceName": "msgraph.generated",
  "language": "Python",
  "usesBackingStore": false,
  "includeAdditionalData": true,
  "serializers": [
    "Microsoft.Kiota.Serialization.Json.JsonSerializationWriterFactory",
    "Microsoft.Kiota.Serialization.Text.TextSerializationWriterFactory",
    "Microsoft.Kiota.Serialization.Form.FormSerializationWriterFactory"
  ],
  "deserializers": [
    "Microsoft.Kiota.Serialization.Json.JsonParseNodeFactory",
    "Microsoft.Kiota.Serialization.Text.TextParseNodeFactory",
    "Microsoft.Kiota.Serialization.Form.FormParseNodeFactory"
  ],
  "structuredMimeTypes": [
    "application/json",
    "text/plain",
    "application/x-www-form-urlencoded"
  ],
  "includePatterns": [],
  "excludePatterns": [],
  "disabledValidationRules": []
}